ocr_tamil/__init__.py
ocr_tamil/ocr.py
ocr_tamil/configs/__init__.py
ocr_tamil/configs/bench.yaml
ocr_tamil/configs/main.yaml
ocr_tamil/configs/tune.yaml
ocr_tamil/configs/charset/36_lowercase.yaml
ocr_tamil/configs/charset/62_mixed-case.yaml
ocr_tamil/configs/charset/94_full.yaml
ocr_tamil/configs/charset/__init__.py
ocr_tamil/configs/experiment/__init__.py
ocr_tamil/configs/experiment/parseq-patch16-224.yaml
ocr_tamil/configs/experiment/parseq-tiny.yaml
ocr_tamil/configs/experiment/parseq.yaml
ocr_tamil/configs/model/__init__.py
ocr_tamil/configs/model/abinet.yaml
ocr_tamil/configs/model/crnn.yaml
ocr_tamil/configs/model/parseq.yaml
ocr_tamil/configs/model/trba.yaml
ocr_tamil/configs/model/vitstr.yaml
ocr_tamil/craft_text_detector/__init__.py
ocr_tamil/craft_text_detector/craft_utils.py
ocr_tamil/craft_text_detector/file_utils.py
ocr_tamil/craft_text_detector/image_utils.py
ocr_tamil/craft_text_detector/predict.py
ocr_tamil/craft_text_detector/setup.py
ocr_tamil/craft_text_detector/torch_utils.py
ocr_tamil/craft_text_detector/models/__init__.py
ocr_tamil/craft_text_detector/models/craftnet.py
ocr_tamil/craft_text_detector/models/refinenet.py
ocr_tamil/craft_text_detector/models/basenet/__init__.py
ocr_tamil/craft_text_detector/models/basenet/vgg16_bn.py
ocr_tamil/strhub/__init__.py
ocr_tamil/strhub/data/__init__.py
ocr_tamil/strhub/data/utils.py
ocr_tamil/strhub/models/__init__.py
ocr_tamil/strhub/models/base.py
ocr_tamil/strhub/models/utils.py
ocr_tamil/strhub/models/parseq/__init__.py
ocr_tamil/strhub/models/parseq/modules.py
ocr_tamil/strhub/models/parseq/system.py
ocr_tamil-0.4.1.dist-info/licenses/LICENSE
ocr_tamil-0.4.1.dist-info/METADATA
ocr_tamil-0.4.1.dist-info/WHEEL
ocr_tamil-0.4.1.dist-info/entry_points.txt
ocr_tamil-0.4.1.dist-info/top_level.txt
ocr_tamil-0.4.1.dist-info/RECORD
