Metadata-Version: 2.4
Name: ocr_tamil
Version: 0.4.1
Summary: Python Tamil OCR package
Home-page: https://github.com/gnana70/tamil_ocr
Author: Gnana Prasath
Author-email: Gnana Prasath <gnana70@gmail.com>
License: MIT License
Project-URL: Homepage, https://github.com/gnana70/tamil_ocr
Keywords: ocr,ocr tamil,tamil,indian ocr,tamil ocr
Classifier: License :: OSI Approved :: MIT License
Classifier: Programming Language :: Python
Classifier: Programming Language :: Python :: 3
Requires-Python: >=3.9
License-File: LICENSE
Requires-Dist: torch>=2
Requires-Dist: torchvision>=0.15.1
Requires-Dist: Pillow>=10.0.0
Requires-Dist: opencv-python
Requires-Dist: Open-Tamil
Requires-Dist: numpy
Requires-Dist: pandas
Requires-Dist: gdown
Requires-Dist: pytorch-lightning>=2.0.0
Requires-Dist: matplotlib
Requires-Dist: scikit-image
Requires-Dist: timm==1.0.10
Provides-Extra: dev
Requires-Dist: black; extra == "dev"
Requires-Dist: bumpver; extra == "dev"
Requires-Dist: isort; extra == "dev"
Requires-Dist: pip-tools; extra == "dev"
Requires-Dist: pytest; extra == "dev"
Dynamic: license-file
